sospcat/__init__.py
sospcat/_static_version.py
sospcat/_version.py
sospcat/compare.py
sospcat/social.py
sospcat/spatial.py
SoSpCAT-0.1.3.dist-info/LICENSE
SoSpCAT-0.1.3.dist-info/METADATA
SoSpCAT-0.1.3.dist-info/WHEEL
SoSpCAT-0.1.3.dist-info/top_level.txt
SoSpCAT-0.1.3.dist-info/RECORD
