Metadata-Version: 2.1
Name: SoSpCAT
Version: 0.1.3
Summary: Social-Spatial Community Assignment Test
Home-page: https://SoSpcATPy.readthedocs.io
Author: Jonas I. Liechti [aut, cre]
Author-email: jonas.i.liechti@gmail.com
License: BSD
Project-URL: Bug Tracker, https://github.com/j-i-l/SoSpCATpy/issues
Project-URL: Documentation, https://sospcatpy.readthedocs.io
Project-URL: Source Code, https://github.com/j-i-l/SoSpCATpy
Keywords: social spatial group cluster groupstructure
Platform: UNKNOWN
Classifier: Intended Audience :: Science/Research
Classifier: Development Status :: 5 - Production/Stable
Classifier: License :: OSI Approved :: BSD License
Classifier: Operating System :: OS Independent
Classifier: Programming Language :: Python :: 3.6
Classifier: Programming Language :: Python :: 3.7
Classifier: Programming Language :: Python :: 3.8
Classifier: Programming Language :: Python
Classifier: Topic :: Scientific/Engineering :: Bio-Informatics
Requires-Dist: python-igraph
Requires-Dist: numpy
Requires-Dist: scikit-learn
